agiltron_selfalign/__init__.py
agiltron_selfalign/module.py
agiltron_selfalign/py.typed
agiltron_selfalign-0.1.0.dist-info/LICENSE
agiltron_selfalign-0.1.0.dist-info/WHEEL
agiltron_selfalign-0.1.0.dist-info/METADATA
agiltron_selfalign-0.1.0.dist-info/RECORD
