Metadata-Version: 2.1
Name: agiltron-selfalign
Version: 0.1.0
Summary: Python interface for the Agiltron SelfAlign fiber switch
Home-page: https://github.com/ograsdijk/Agiltron-SelfAlign
License: MIT
Author: ograsdijk
Author-email: o.grasdijk@gmail.com
Requires-Python: >=3.8
Classifier: License :: OSI Approved :: MIT License
Classifier: Programming Language :: Python :: 3
Classifier: Programming Language :: Python :: 3.8
Classifier: Programming Language :: Python :: 3.9
Classifier: Programming Language :: Python :: 3.10
Requires-Dist: PyVISA (>=1.13.0,<2.0.0)
Project-URL: Repository, https://github.com/ograsdijk/Agiltron-SelfAlign
